base_assistant_extension/__init__.py
base_assistant_extension/base_extension.py
base_assistant_extension/entry.py
base_assistant_extension/extension_agent_factory.py
base_assistant_extension/extension_host.py
base_assistant_extension/extension_metadata.py
base_assistant_extension-0.6.6.dist-info/LICENSE
base_assistant_extension-0.6.6.dist-info/METADATA
base_assistant_extension-0.6.6.dist-info/WHEEL
base_assistant_extension-0.6.6.dist-info/RECORD
