Metadata-Version: 2.1
Name: base-assistant-extension
Version: 0.6.6
Summary: 
License: MIT
Author: Samuel
Author-email: samuelint@gmail.com
Requires-Python: >=3.9,<3.13
Classifier: License :: OSI Approved :: MIT License
Classifier: Programming Language :: Python :: 3
Classifier: Programming Language :: Python :: 3.9
Classifier: Programming Language :: Python :: 3.10
Classifier: Programming Language :: Python :: 3.11
Classifier: Programming Language :: Python :: 3.12
Provides-Extra: host-dependencies
Requires-Dist: fastapi (>=0.112.0) ; extra == "host-dependencies"
Requires-Dist: langchain (>=0.2.6) ; extra == "host-dependencies"
Requires-Dist: langchain-openai (>=0.1.20) ; extra == "host-dependencies"
Requires-Dist: langchain-openai-api-bridge (>=0.11.1)
Requires-Dist: langgraph (>=0.1.19) ; extra == "host-dependencies"
Requires-Dist: uvicorn (>=0.30.5) ; extra == "host-dependencies"
